{"sections":{"main":{"type":"main-page","disabled":true,"settings":{}},"slideshow_Eck3LB":{"type":"slideshow","blocks":{"image_MyV3NC":{"type":"image","settings":{"top_subheading":"","title":"THE HERITAGE COLLECTION","title_size":70,"subheading":"Dropping Soon","link":"","link_text":"","link_2":"","link_text_2":"","color_accent":"rgba(0,0,0,0)","text_align":"vertical-bottom horizontal-center","image":"shopify:\/\/shop_images\/Heritage_Necklace.jpg","parallax_direction":"top","overlay_opacity":0}}},"block_order":["image_MyV3NC"],"settings":{"section_height":"650px","mobile_height":"auto","parallax":false,"style":"bars","autoplay":false,"autoplay_speed":5,"lazyload_images":true}},"the_luxe_collection_mVJzKK":{"type":"the-luxe-collection","blocks":{"collection_GNcmRT":{"type":"collection","settings":{"heading":"Majestic Collection","collection_title":"IRRESISTIBLY MAGNETIC","description":"Notable center stones and intricate design with eye-catching brilliance.","link_title":"EXPLORE MAJESTIC","link_url":"shopify:\/\/pages\/majestic-collection-engagement-rings-and-jewelry"}},"collection_3kJkhf":{"type":"collection","settings":{"heading":"Heritage Collection","collection_title":"EVERLASTING ATTRACTION","description":"Uncover a sense of nostalgia where vintage design meets modern day essence.","link_title":"EXPLORE HERITAGE","link_url":"shopify:\/\/pages\/heritage-collection-engagement-rings-and-jewelry"}},"collection_3cDHmy":{"type":"collection","settings":{"heading":"Illuminate Collection","collection_title":"DREAMLIKE DIAMONDS","description":"Romantic style harmoniously intertwines with contemporary elegance.","link_title":"EXPLORE ILLUMINATE","link_url":"shopify:\/\/pages\/illuminate-collection-engagement-rings-and-jewelry"}},"collection_yzT8YH":{"type":"collection","settings":{"heading":"Elegance Collection","collection_title":"BREATHTAKING BEAUTY","description":"Quiet luxury merges with classic style to leave an effortless impression.","link_title":"EXPLORE ELEGANCE","link_url":"shopify:\/\/pages\/elegance-collection-engagement-rings-and-jewelry"}},"collection_ddzLEr":{"type":"collection","settings":{"heading":"The Haute Collection","collection_title":"UNFORGETTABLY BOLD","description":"Notable center stones and intricate design with eye-catching brilliance.","link_title":"EXPLORE HAUTE","link_url":"shopify:\/\/pages\/haute-collection-engagement-rings-and-jewelry"}}},"block_order":["collection_GNcmRT","collection_3kJkhf","collection_3cDHmy","collection_yzT8YH","collection_ddzLEr"],"disabled":true,"settings":{"description":""}}},"order":["main","slideshow_Eck3LB","the_luxe_collection_mVJzKK"]}